{
  "assigned": {
    "2025-01": {
      "held": "33",
      "categories": {
        "investments": "200",
        "rent": "800",
        "utilities": "150",
        "car": "580",
        "hobbies": "50",
        "rainy-day-fund": "16",
        "eating-out": "99.34"
      }
    },
    "2025-02": {
      "held": "0",
      "categories": {
        "rainy-day-fund": "800"
      }
    },
    "2025-08": {
      "held": "0",
      "categories": {
        "car": "67.66",
        "rainy-day-fund": "-263"
      }
    }
  }
}